AUTHORS.md
CHANGES.md
cgranges/.git
cgranges/.gitignore
cgranges/LICENSE.txt
cgranges/Makefile
cgranges/README.md
cgranges/cgranges.c
cgranges/cgranges.h
cgranges/cpp/IITree.h
cgranges/cpp/Makefile
cgranges/cpp/example.cpp
cgranges/example
cgranges/example.c
cgranges/khash.h
cgranges/python/README.rst
cgranges/python/cgranges.c
cgranges/python/cgranges.pyx
cgranges/setup.py
cgranges/test/3rd-party/AIList/AIList.c
cgranges/test/3rd-party/AIList/AIList.h
cgranges/test/3rd-party/AITree/AITree.c
cgranges/test/3rd-party/AITree/compiler.h
cgranges/test/3rd-party/AITree/interval_tree.c
cgranges/test/3rd-party/AITree/interval_tree.h
cgranges/test/3rd-party/AITree/interval_tree_generic.h
cgranges/test/3rd-party/AITree/rbtree.c
cgranges/test/3rd-party/AITree/rbtree.h
cgranges/test/3rd-party/AITree/rbtree_augmented.h
cgranges/test/3rd-party/NCList/intervaldb.c
cgranges/test/3rd-party/NCList/intervaldb.h
cgranges/test/3rd-party/README.md
cgranges/test/IntervalTree.h
cgranges/test/Makefile
cgranges/test/bedcov-cr
cgranges/test/bedcov-cr.c
cgranges/test/bedcov-cr.dSYM/Contents/Info.plist
cgranges/test/bedcov-cr.dSYM/Contents/Resources/DWARF/bedcov-cr
cgranges/test/bedcov-cr.js
cgranges/test/bedcov-cr.py
cgranges/test/bedcov-cr1.py
cgranges/test/bedcov-cr2.py
cgranges/test/bedcov-iitree
cgranges/test/bedcov-iitree.cpp
cgranges/test/bedcov-iitree.dSYM/Contents/Info.plist
cgranges/test/bedcov-iitree.dSYM/Contents/Resources/DWARF/bedcov-iitree
cgranges/test/bedcov-itree.cpp
cgranges/test/bedcov-naive.js
cgranges/test/bedcov-ncls.py
cgranges/test/bedcov-qs.py
cgranges/test/kseq.h
cgranges/test/test1.bed
cgranges/test/test2.bed
indextools/__init__.py
indextools/bed.py
indextools/console/__init__.py
indextools/console/commands.py
indextools/console/features.py
indextools/console/partition.py
indextools/console/split.py
indextools/index.py
indextools/intervals.py
indextools/regions.py
indextools/utils.py
cgranges.cpython-36m-darwin.so
indextools-0.1.4.dist-info/entry_points.txt
indextools-0.1.4.dist-info/LICENSE
indextools-0.1.4.dist-info/WHEEL
indextools-0.1.4.dist-info/METADATA
indextools-0.1.4.dist-info/RECORD
