Metadata-Version: 2.1
Name: indextools
Version: 0.1.4
Summary: A toolkit for accelerating genomics using index files.
Home-page: https://github.com/dnanexus/indextools
License: MIT
Author: John Didion
Author-email: jdidion@dnanexus.com
Requires-Python: >=3.6,<4.0
Classifier: Development Status :: 4 - Beta
Classifier: License :: OSI Approved :: MIT License
Classifier: Programming Language :: Python :: 3
Classifier: Programming Language :: Python :: 3.6
Classifier: Programming Language :: Python :: 3.7
Provides-Extra: jinja2
Requires-Dist: autoclick (>=0.6.1,<0.7.0)
Requires-Dist: loguru (>=0.3.2,<0.4.0)
Requires-Dist: ngsindex (>=0.1.7,<0.2.0)
Requires-Dist: pysam (>=0.15,<0.16)
Requires-Dist: xphyle (>=4.1.3,<5.0.0)
Project-URL: Repository, https://github.com/dnanexus/indextools.git
